setup.py
tests/__init__.py
tests/geocoders/__init__.py
tests/geocoders/test_google_v3.py
tornado_geopy/__init__.py
tornado_geopy.egg-info/PKG-INFO
tornado_geopy.egg-info/SOURCES.txt
tornado_geopy.egg-info/dependency_links.txt
tornado_geopy.egg-info/entry_points.txt
tornado_geopy.egg-info/requires.txt
tornado_geopy.egg-info/top_level.txt
tornado_geopy/geocoders/__init__.py
tornado_geopy/geocoders/google_v3.py