Metadata-Version: 1.1
Name: tornado-geopy
Version: 0.1.0
Summary: tornado-geopy is an asynchronous version of the awesome geopy library.
Home-page: http://github.com/heynemann/tornado-geopy/
Author: Bernardo Heynemann
Author-email: heynemann@gmail.com
License: MIT
Keywords: geocoding locations google apis
Platform: UNKNOWN
Classifier: Development Status :: 4 - Beta
Classifier: Intended Audience :: Developers
Classifier: License :: OSI Approved :: MIT License
Classifier: Natural Language :: English
Classifier: Operating System :: MacOS
Classifier: Operating System :: POSIX
Classifier: Operating System :: Unix
Classifier: Operating System :: OS Independent
Classifier: Programming Language :: Python :: 2.7
Classifier: Programming Language :: Python :: 3.3
